PawanAi_STT/__init__.py
PawanAi_STT-0.1.dist-info/METADATA
PawanAi_STT-0.1.dist-info/WHEEL
PawanAi_STT-0.1.dist-info/top_level.txt
PawanAi_STT-0.1.dist-info/RECORD
