Metadata-Version: 2.1
Name: PawanAi_STT
Version: 0.1
Summary: this is speech to text package created by pawan kumar
Author: Pawan Kumar
Author-email: pawanku.sbp@gmail.com
